mcsniperpy/__init__.py
mcsniperpy/__main__.py
mcsniperpy/cli.py
mcsniperpy/sniper.py
mcsniperpy/util/__init__.py
mcsniperpy/util/announce.py
mcsniperpy/util/logs_manager.py
mcsniperpy/util/name_system.py
mcsniperpy/util/ping_tester.py
mcsniperpy/util/request_manager.py
mcsniperpy/util/utils.py
mcsniperpy/util/classes/__init__.py
mcsniperpy/util/classes/account.py
mcsniperpy/util/classes/config.py
MCsniperPY-3.5.dist-info/LICENSE
MCsniperPY-3.5.dist-info/METADATA
MCsniperPY-3.5.dist-info/WHEEL
MCsniperPY-3.5.dist-info/entry_points.txt
MCsniperPY-3.5.dist-info/top_level.txt
MCsniperPY-3.5.dist-info/RECORD
