Metadata-Version: 2.1
Name: MCsniperPY
Version: 3.5
Summary: Minecraft name sniper written in Python
Home-page: https://mcsniperpy.com
Author: Kqzz
License: MIT
Project-URL: GitHub, https://github.com/MCsniperPY/MCsniperPY
Project-URL: Documentation, https://docs.mcsniperpy.com
Platform: UNKNOWN
Classifier: Development Status :: 4 - Beta
Classifier: License :: OSI Approved :: MIT License
Classifier: Programming Language :: Python :: 3.8
Classifier: Programming Language :: Python :: 3.9
Requires-Python: >=3.8
License-File: LICENSE
Requires-Dist: typer
Requires-Dist: colorama
Requires-Dist: aiohttp
Requires-Dist: bs4
